cleanapi/__init__.py
cleanapi/server.py
cleanapi/logger/__init__.py
cleanapi/logger/server_logger.py
cleanapi/third_party_libs/__init__.py
cleanapi/third_party_libs/importdir.py
handlers/__init__.py
handlers/pydantic_handler.py
handlers/simple_handler.py
cleanapi-0.1.6.dist-info/LICENSE
cleanapi-0.1.6.dist-info/METADATA
cleanapi-0.1.6.dist-info/WHEEL
cleanapi-0.1.6.dist-info/top_level.txt
cleanapi-0.1.6.dist-info/RECORD
