Metadata-Version: 2.1
Name: cleanapi
Version: 0.1.6
Summary: Pretty tornado wrapper for making lightweight REST API services
Home-page: https://github.com/vlakir/cleanapi.git
Author: Vladimir Kirievskiy
Author-email: vlakir1234@gmail.com
License: UNKNOWN
Platform: UNKNOWN
Classifier: Programming Language :: Python :: 3.9
Classifier: License :: OSI Approved :: GNU General Public License v3 (GPLv3)
Classifier: Topic :: Internet :: WWW/HTTP :: HTTP Servers
License-File: LICENSE
Requires-Dist: tornado (>=6.1)
Requires-Dist: pydantic (>=1.8.2)
Requires-Dist: asgiref (>=3.3.4)
Requires-Dist: docutils (>=0.17.1)
Requires-Dist: cryptography (>=3.4.7)
Requires-Dist: keyring (>=23.1.0)
Requires-Dist: requests (>=2.26.0)
Requires-Dist: colorama (>=0.4.4)
Requires-Dist: rfc3986 (>=1.5.0)
Requires-Dist: pkginfo (>=1.7.1)
Requires-Dist: tqdm (>=4.62.2)
Requires-Dist: urllib3 (>=1.26.6)
Requires-Dist: six (>=1.16.0)
Requires-Dist: webencodings (>=0.5.1)
Requires-Dist: packaging (>=21.0)
Requires-Dist: bleach (>=4.0.0)
Requires-Dist: certifi (>=2021.5.30)
Requires-Dist: jeepney (>=0.7.1)
Requires-Dist: SecretStorage (>=3.3.1)
Requires-Dist: idna (>=3.2)
Requires-Dist: Pygments (>=2.10.0)
Requires-Dist: pyparsing (>=2.4.7)
Requires-Dist: pycparser (>=2.20)
Requires-Dist: zipp (>=3.5.0)
